https/HTTPSServer.py
https/__init__.py
https/server.py
quick_https-0.1.1.dist-info/licenses/LICENSE.txt
quick_https-0.1.1.dist-info/METADATA
quick_https-0.1.1.dist-info/WHEEL
quick_https-0.1.1.dist-info/top_level.txt
quick_https-0.1.1.dist-info/RECORD
