Metadata-Version: 2.4
Name: quick-https
Version: 0.1.1
Summary: Expanding python's HTTPServer to use HTTPS
Home-page: https://github.com/samfelt/simpleWebServer
Author: samfelt
Classifier: Programming Language :: Python :: 3
Classifier: Programming Language :: Python :: 3.7
Classifier: Programming Language :: Python :: 3.8
Classifier: Programming Language :: Python :: 3.9
Classifier: Programming Language :: Python :: 3.10
Classifier: License :: OSI Approved :: GNU General Public License v3 or later (GPLv3+)
License-File: LICENSE.txt
Requires-Dist: cryptography>=37.0.4
Requires-Dist: multipart>=1.2.1
Provides-Extra: dev
Requires-Dist: pre-commit>=2.20.0; extra == "dev"
Requires-Dist: pytest>=7.1.3; extra == "dev"
Dynamic: license-file
